nextmusic/__init__.py
nextmusic/_classes.py
nextmusic/_version.py
nextmusic/checks.py
nextmusic/errors.py
nextmusic/events.py
nextmusic/ext.py
nextmusic/music.py
nextmusic/paginator.py
nextmusic/player.py
nextmusic-0.0.6.dist-info/LICENCE
nextmusic-0.0.6.dist-info/METADATA
nextmusic-0.0.6.dist-info/WHEEL
nextmusic-0.0.6.dist-info/top_level.txt
nextmusic-0.0.6.dist-info/RECORD
