Metadata-Version: 2.1
Name: nextmusic
Version: 0.0.6
Summary: Music cog for discord bots. Supports YouTube, YoutubeMusic, SoundCloud and Spotify.
Home-page: https://github.com/PranoyPlayz/nextmusic.git
Author: Pranoy Majumdar
Author-email: officialpranoy2@gmail.com
License: MIT
Keywords: nextcord nextcord-music discord-music music-bot nextcord-music-bot discord-music-bot lavalink wavelink nextmusic
Classifier: Development Status :: 5 - Production/Stable
Classifier: Intended Audience :: Developers
Classifier: Framework :: aiohttp
Classifier: Operating System :: MacOS
Classifier: Operating System :: POSIX :: Linux
Classifier: Operating System :: Microsoft :: Windows
Classifier: License :: OSI Approved :: MIT License
Classifier: Programming Language :: Python :: 3.7
Classifier: Programming Language :: Python :: 3.8
Classifier: Programming Language :: Python :: 3.9
Classifier: Programming Language :: Python :: 3.10
Requires-Python: >=3.7, <4
License-File: LICENCE
Requires-Dist: async-timeout
Requires-Dist: wavelink
Requires-Dist: nextcord
Requires-Dist: psutil
Requires-Dist: rich
Requires-Dist: motor
Requires-Dist: pymongo
Requires-Dist: pymongo[srv]
